{"Boston College:Cleveland Circle":{"name":"Kenmore","longitude_comma_latitude":"42.348949,-71.095169"},"Boston College:Forest Hills":{"name":"Downtown Crossing","longitude_comma_latitude":"42.355518,-71.060225"},"Boston College:Heath Street":{"name":"Copley","longitude_comma_latitude":"42.349974,-71.077447"},"Boston College:Riverside":{"name":"Kenmore","longitude_comma_latitude":"42.348949,-71.095169"},"Cleveland Circle:Boston College":{"name":"Kenmore","longitude_comma_latitude":"42.348949,-71.095169"},"Cleveland Circle:Forest Hills":{"name":"Downtown Crossing","longitude_comma_latitude":"42.355518,-71.060225"},"Cleveland Circle:Heath Street":{"name":"Copley","longitude_comma_latitude":"42.349974,-71.077447"},"Cleveland Circle:Riverside":{"name":"Kenmore","longitude_comma_latitude":"42.348949,-71.095169"},"Forest Hills:Boston College":{"name":"Park Street","longitude_comma_latitude":"42.356395,-71.062424"},"Forest Hills:Cleveland Circle":{"name":"Park Street","longitude_comma_latitude":"42.356395,-71.062424"},"Forest Hills:Heath Street":{"name":"Park Street","longitude_comma_latitude":"42.356395,-71.062424"},"Forest Hills:Riverside":{"name":"Park Street","longitude_comma_latitude":"42.356395,-71.062424"},"Heath Street:Boston College":{"name":"Copley","longitude_comma_latitude":"42.349974,-71.077447"},"Heath Street:Cleveland Circle":{"name":"Copley","longitude_comma_latitude":"42.349974,-71.077447"},"Heath Street:Forest Hills":{"name":"Downtown Crossing","longitude_comma_latitude":"42.355518,-71.060225"},"Heath Street:Riverside":{"name":"Copley","longitude_comma_latitude":"42.349974,-71.077447"},"Riverside:Boston College":{"name":"Kenmore","longitude_comma_latitude":"42.348949,-71.095169"},"Riverside:Cleveland Circle":{"name":"Kenmore","longitude_comma_latitude":"42.348949,-71.095169"},"Riverside:Forest Hills":{"name":"Downtown Crossing","longitude_comma_latitude":"42.355518,-71.060225"},"Riverside:Heath Street":{"name":"Copley","longitude_comma_latitude":"42.349974,-71.077447"}}